{"hotelId":"77472eb4-21c6-4b6b-8be0-c822d79c3777","slug":"grand-plaza-hotel","title":"Grand Plaza Hotel Updated","description":"A luxury hotel in the city center with updated features","guestCount":200,"bedroomCount":100,"bathroomCount":80,"amenities":["Wi-Fi","Pool","Gym","Spa"],"hostInfo":"Jane Doe","address":"456 New Plaza, Downtown","latitude":40.7334,"longitude":-74.0158,"images":[],"rooms":[{"roomSlug":"luxury-suite","roomTitle":"Luxury Suite","bedroomCount":2,"roomImage":""},{"roomSlug":"standard-room","roomTitle":"Standard Room","bedroomCount":1,"roomImage":""}]}
